state_saver/__init__.py
state_saver/saver.py
state_saver-1.4.dist-info/LICENSE
state_saver-1.4.dist-info/METADATA
state_saver-1.4.dist-info/WHEEL
state_saver-1.4.dist-info/top_level.txt
state_saver-1.4.dist-info/RECORD
