Metadata-Version: 2.1
Name: state-saver
Version: 1.4
Summary: File control for keeping your state
Home-page: UNKNOWN
Author: Petar Nikolov
Author-email: p.bijev@gmail.com
License: UNKNOWN
Platform: UNKNOWN
License-File: LICENSE
